pytse_filter/__init__.py
pytse_filter/calculate_client_data.py
pytse_filter/calculate_indicators.py
pytse_filter/client_setting.py
pytse_filter/config.py
pytse_filter/download_history.py
pytse_filter/download_realtime.py
pytse_filter/history.py
pytse_filter/inds_setting.py
pytse_filter/realtime.py
pytse_filter/syms.json
pytse_filter/syms_manager.py
pytse_filter-1.45.dist-info/METADATA
pytse_filter-1.45.dist-info/WHEEL
pytse_filter-1.45.dist-info/license.md
pytse_filter-1.45.dist-info/top_level.txt
pytse_filter-1.45.dist-info/RECORD
