Metadata-Version: 2.1
Name: pytse_filter
Version: 1.45
Summary: A user-friendly project to filter symbols of Tehran Stock Exchange
Home-page: https://github.com/farhad-mohammadi/pytse_filter
Author: Farhad Mohammadi
Author-email: farhad.mohammadi60@gmail.com
License: MIT License
Classifier: Programming Language :: Python :: 3
Classifier: License :: OSI Approved :: MIT License
Classifier: Operating System :: OS Independent
Classifier: Development Status :: 3 - Alpha
Classifier: Intended Audience :: Financial and Insurance Industry
Classifier: Topic :: Office/Business :: Financial :: Investment
Requires-Python: >=3.6
License-File: license.md
Requires-Dist: certifi ==2024.2.2
Requires-Dist: charset-normalizer ==3.3.2
Requires-Dist: colorama ==0.4.6
Requires-Dist: et-xmlfile ==1.1.0
Requires-Dist: idna ==3.6
Requires-Dist: numpy ==1.24.4
Requires-Dist: openpyxl ==3.1.2
Requires-Dist: pandas ==2.2.1
Requires-Dist: pandas-ta ==0.3.14b0
Requires-Dist: pyarrow ==15.0.0
Requires-Dist: python-dateutil ==2.8.2
Requires-Dist: pytz ==2024.1
Requires-Dist: requests ==2.31.0
Requires-Dist: six ==1.16.0
Requires-Dist: tqdm ==4.66.2
Requires-Dist: tzdata ==2024.1
Requires-Dist: urllib3 ==2.2.1
Requires-Dist: jalali-core ==1.0.0
Requires-Dist: jdatetime ==5.0.0
Requires-Dist: lxml ==5.2.1
